covidcloud_search/__init__.py
covidcloud_search/search.py
covidcloud_search-0.1.1.dist-info/METADATA
covidcloud_search-0.1.1.dist-info/WHEEL
covidcloud_search-0.1.1.dist-info/top_level.txt
covidcloud_search-0.1.1.dist-info/RECORD
